{"pagination":{},"meta":{"code":200},"data":[{"attribution":null,"tags":["vrijdag"],"type":"image","location":{"latitude":52.2240601,"name":"Tabakhuis","longitude":5.4832301,"id":442252184},"comments":{"count":0},"filter":"Normal","created_time":"1449243176","link":"https:\/\/www.instagram.com\/p\/-4AOsSOx9j\/","likes":{"count":1},"images":{"low_resolution":{"url":"https:\/\/scontent.cdninstagram.com\/hphotos-xtf1\/t51.2885-15\/s320x320\/e35\/12292716_1502671130061344_468458098_n.jpg","width":320,"height":320},"thumbnail":{"url":"https:\/\/scontent.cdninstagram.com\/hphotos-xtf1\/t51.2885-15\/s150x150\/e35\/12292716_1502671130061344_468458098_n.jpg","width":150,"height":150},"standard_resolution":{"url":"https:\/\/scontent.cdninstagram.com\/hphotos-xtf1\/t51.2885-15\/s640x640\/sh0.08\/e35\/12292716_1502671130061344_468458098_n.jpg","width":640,"height":640}},"users_in_photo":[],"caption":{"created_time":"1449243176","text":"Tabakhuis #vrijdag","from":{"username":"stijnvdvegt","profile_picture":"https:\/\/scontent.cdninstagram.com\/hphotos-xfa1\/t51.2885-19\/11906329_960233084022564_1448528159_a.jpg","id":"231408782","full_name":"Stijn van der Vegt"},"id":"1132656324563901598"},"user_has_liked":false,"id":"1132656315906858851_231408782","user":{"username":"stijnvdvegt","profile_picture":"https:\/\/scontent.cdninstagram.com\/hphotos-xfa1\/t51.2885-19\/11906329_960233084022564_1448528159_a.jpg","id":"231408782","full_name":"Stijn van der Vegt"}}]}